[
    {
        "name": "Projects1",
        "metadata": {
            "link": "https://www.example.com",
            "image": "https://cdn-community.codemao.cn/47/community/d2ViXzMwMDFfMzUyMzQwMl8wXzE3MTc5NTQ0ODczNTVfZGE0MDUwMTA.png",
            "subtitle": "description1"
        }
    },
    {
        "name": "Projects2",
        "metadata": {
            "link": "https://www.example.com",
            "image": "https://cdn-community.codemao.cn/47/community/d2ViXzMwMDFfMzUyMzQwMl8wXzE3MTc5NTQ0ODczNTVfZGE0MDUwMTA.png",
            "subtitle": "description2"
        }
    },
    {
        "name": "Projects3",
        "metadata": {
            "link": "https://www.example.com",
            "image": "https://cdn-community.codemao.cn/47/community/d2ViXzMwMDFfMzUyMzQwMl8wXzE3MTc5NTQ0ODczNTVfZGE0MDUwMTA.png",
            "subtitle": "description3"
        }
    }
]